complex_detector/Moore/moore_seq.v
module moore_seq(
    input x,
    input clk,
    input rst_b,
    output y
);

    localparam S0 = 3'b000;
    localparam S1 = 3'b001;
    localparam S2 = 3'b010;
    localparam S3 = 3'b011;
    localparam S4 = 3'b100;

    reg [2:0] PresentState, NextState;

    always @(posedge clk or negedge rst_b) begin 
        if(!rst_b) PresentState <= S0;
        else PresentState <= NextState;
    end

    always @(PresentState,x) begin 
        case(PresentState)
        S0: NextState = (x)? S1:S0;
        S1: NextState = (x)? S2:S0;
        S2: NextState = (x)? S3:S4;
        S3: NextState = (x)? S3:S4;
        S4: NextState = (x)? S1:S0;
        endcase
    end

    assign y = (PresentState == S4)|(PresentState == S3);

endmodule

complex_detector/Moore/moore_seq_tb.v
`timescale 1ns/1ps
module moore_seq_tb();

reg clk,x,rst_b;
wire y;

moore_seq DUT(
    .x(x),
    .y(y),
    .clk(clk),
    .rst_b(rst_b)  
);

initial begin
    clk = 1'b0;
    forever begin
        #5 clk = ~clk;
    end    
end

initial begin 
    rst_b = 1'b0;
    x = 1'b0;

    #3 x=1'b0; rst_b = 1'b1;
    #10 x=1'b1;
    #10 x=1'b0;
    #10 x=1'b1;
    #10 x = 1'b1;
    #10 x = 1'b1;
    #10 x = 1'b1;
    #10 x = 1'b0;
    #10 x = 1'b0;
    #10 x = 1'b1;
    #10 x = 1'b1;
    #10 x = 1'b1;
    #10 x = 1'b1;
    #10 x = 1'b0;
    #10 x = 1'b1;
    #10 x = 1'b1;
    #10 x = 1'b0;
    #5 $finish;
end

initial begin
    $dumpfile("moore_detector.vcd");
    $dumpvars(0, moore_seq_tb);
end

endmodule

complex_detector/Moore/moore_detector.vcd
$date
	Sat Sep  6 17:42:40 2025
$end
$version
	Icarus Verilog
$end
$timescale
	1ps
$end
$scope module moore_seq_tb $end
$var wire 1 ! y $end
$var reg 1 " clk $end
$var reg 1 # rst_b $end
$var reg 1 $ x $end
$scope module DUT $end
$var wire 1 " clk $end
$var wire 1 # rst_b $end
$var wire 1 $ x $end
$var wire 1 ! y $end
$var reg 3 % NextState [2:0] $end
$var reg 3 & PresentState [2:0] $end
$upscope $end
$upscope $end
$enddefinitions $end
#0
$dumpvars
b0 &
b0 %
0$
0#
0"
0!
$end
#3000
1#
#5000
1"
#10000
0"
#13000
b1 %
1$
#15000
b10 %
b1 &
1"
#20000
0"
#23000
b0 %
0$
#25000
b0 &
1"
#30000
0"
#33000
b1 %
1$
#35000
b10 %
b1 &
1"
#40000
0"
#45000
b11 %
b10 &
1"
#50000
0"
#55000
1!
b11 &
1"
#60000
0"
#65000
1"
#70000
0"
#73000
b100 %
0$
#75000
b0 %
b100 &
1"
#80000
0"
#85000
0!
b0 &
1"
#90000
0"
#93000
b1 %
1$
#95000
b10 %
b1 &
1"
#100000
0"
#105000
b11 %
b10 &
1"
#110000
0"
#115000
1!
b11 &
1"
#120000
0"
#125000
1"
#130000
0"
#133000
b100 %
0$
#135000
b0 %
b100 &
1"
#140000
0"
#143000
b1 %
1$
#145000
b10 %
0!
b1 &
1"
#150000
0"
#155000
b11 %
b10 &
1"
#160000
0"
#163000
b100 %
0$
#165000
b0 %
1!
b100 &
1"
