11_detector/Mealy/mealy_seq.v
/*module mealy_seq(
    input x,
    input clk,
    input rst_b,
    output y
);

    localparam S0= 1'b0;
    localparam S1= 1'b1;

    reg NextState, PresentState;

    always @(posedge clk or negedge rst_b) begin
        if(!rst_b) PresentState <= S0;
        else PresentState <= NextState;
    end

    always @(x,PresentState) begin 
        case(PresentState) 
        S0: NextState = (x)? S1:S0;
        S1: NextState = (x)? S1:S0;
        endcase
    end

    assign y = (PresentState == S1) & (x==1);

endmodule*/


module mealy_seq(
    input x,
    input clk,
    input rst_b,
    output y
);

    localparam S0 = 1'b0;
    localparam S1 = 1'b1;

    reg PresentState, NextState;

    always @(posedge clk or negedge rst_b) begin
        if(!rst_b) PresentState <= S0;
        else PresentState <= NextState;
    end

    always @(PresentState, x) begin 
        case(PresentState)
        S0: NextState = (x)? S1:S0;
        S1: NextState = (x)? S1:S0;
        endcase
    end

    assign y = (PresentState == S1) & x;


endmodule

11_detector/Mealy/mealy_seq_tb.v
`timescale 1ns/1ps
module mealy_seq_tb();

reg clk,x,rst_b;
wire y;

mealy_seq DUT(
    .x(x),
    .y(y),
    .clk(clk),
    .rst_b(rst_b)  
);

initial begin
    clk = 1'b0;
    forever begin
        #5 clk = ~clk;
    end    
end

initial begin 
    rst_b = 1'b0;
    x = 1'b0;

    #3 x=1'b0; rst_b = 1'b1;
    #10 x=1'b1;
    #10 x=1'b0;
    #10 x=1'b1;
    #10 x = 1'b1;
    #10 x = 1'b1;
    #5 $finish;
end

initial begin
    $dumpfile("mealy_detector_11.vcd");
    $dumpvars(0, mealy_seq_tb);
end

endmodule

11_detector/Mealy/mealy_detector_11.vcd
$date
	Sat Sep  6 20:09:49 2025
$end
$version
	Icarus Verilog
$end
$timescale
	1ps
$end
$scope module mealy_seq_tb $end
$var wire 1 ! y $end
$var reg 1 " clk $end
$var reg 1 # rst_b $end
$var reg 1 $ x $end
$scope module DUT $end
$var wire 1 " clk $end
$var wire 1 # rst_b $end
$var wire 1 $ x $end
$var wire 1 ! y $end
$var reg 1 % NextState $end
$var reg 1 & PresentState $end
$upscope $end
$upscope $end
$enddefinitions $end
#0
$dumpvars
0&
0%
0$
0#
0"
0!
$end
#3000
1#
#5000
1"
#10000
0"
#13000
1%
1$
#15000
1!
1&
1"
#20000
0"
#23000
0!
0%
0$
#25000
0&
1"
#30000
0"
#33000
1%
1$
#35000
1!
1&
1"
